[{"name":"sql.active_record","payload":{"sql":"SELECT  \"users\".* FROM \"users\"  WHERE \"users\".\"id\" = 8 LIMIT 1","name":"User Load","connection_id":70309411044380,"statement_name":null,"binds":[],"line":10,"filename":"/Users/gafrong/flikr/app/controllers/application_controller.rb","method":"current_user"},"time":"2014-11-22T08:32:38.619+11:00","transaction_id":"84ce9093765909ee8727","end":"2014-11-22T08:32:38.620+11:00","children":[],"duration":0.803},{"name":"sql.active_record","payload":{"sql":"SELECT  \"users\".* FROM \"users\"  WHERE \"users\".\"id\" = 8 LIMIT 1","binds":[],"name":"CACHE","connection_id":70309411044380,"line":10,"filename":"/Users/gafrong/flikr/app/controllers/application_controller.rb","method":"current_user"},"time":"2014-11-22T08:32:38.621+11:00","transaction_id":"af2ba71234e02bb5d0b1","end":"2014-11-22T08:32:38.621+11:00","children":[],"duration":0.213},{"name":"sql.active_record","payload":{"sql":"SELECT \"items\".* FROM \"items\"  WHERE (gender='male' OR gender='unisex')","name":"Item Load","connection_id":70309411044380,"statement_name":null,"binds":[],"line":183,"filename":"/Users/gafrong/flikr/app/controllers/items_controller.rb","method":"category_all"},"time":"2014-11-22T08:32:38.623+11:00","transaction_id":"84ce9093765909ee8727","end":"2014-11-22T08:32:38.665+11:00","children":[],"duration":41.914},{"name":"sql.active_record","payload":{"sql":"SELECT COUNT(*) FROM \"histories\"  WHERE \"histories\".\"user_id\" = $1","name":null,"connection_id":70309411044380,"statement_name":"a1","binds":[[{"oid_type":{},"array":false,"name":"user_id","sql_type":"integer","null":true,"limit":null,"precision":null,"scale":null,"type":"integer","default":null,"default_function":null,"primary":null,"coder":null},8]],"line":204,"filename":"/Users/gafrong/flikr/app/controllers/items_controller.rb","method":"next_item"},"time":"2014-11-22T08:32:38.832+11:00","transaction_id":"84ce9093765909ee8727","end":"2014-11-22T08:32:38.833+11:00","children":[],"duration":0.5860000000000001},{"name":"sql.active_record","payload":{"sql":"SELECT \"histories\".* FROM \"histories\"  WHERE \"histories\".\"user_id\" = $1 AND \"histories\".\"liked\" = 't'","name":"History Load","connection_id":70309411044380,"statement_name":"a2","binds":[[{"oid_type":{},"array":false,"name":"user_id","sql_type":"integer","null":true,"limit":null,"precision":null,"scale":null,"type":"integer","default":null,"default_function":null,"primary":null,"coder":null},8]],"line":222,"filename":"/Users/gafrong/flikr/app/controllers/items_controller.rb","method":"next_item"},"time":"2014-11-22T08:32:38.835+11:00","transaction_id":"84ce9093765909ee8727","end":"2014-11-22T08:32:38.835+11:00","children":[],"duration":0.5479999999999999},{"name":"sql.active_record","payload":{"sql":"SELECT  \"items\".* FROM \"items\"  WHERE \"items\".\"id\" = $1 LIMIT 1","name":"Item Load","connection_id":70309411044380,"statement_name":"a3","binds":[[{"oid_type":{},"array":false,"name":"id","sql_type":"integer","null":false,"limit":null,"precision":null,"scale":null,"type":"integer","default":null,"default_function":"nextval('items_id_seq'::regclass)","primary":null,"coder":null},12204]],"line":222,"filename":"/Users/gafrong/flikr/app/controllers/items_controller.rb","method":"block in next_item"},"time":"2014-11-22T08:32:38.837+11:00","transaction_id":"84ce9093765909ee8727","end":"2014-11-22T08:32:38.838+11:00","children":[],"duration":0.522},{"name":"sql.active_record","payload":{"sql":"SELECT  \"items\".* FROM \"items\"  WHERE \"items\".\"id\" = $1 LIMIT 1","name":"Item Load","connection_id":70309411044380,"statement_name":"a3","binds":[[{"oid_type":{},"array":false,"name":"id","sql_type":"integer","null":false,"limit":null,"precision":null,"scale":null,"type":"integer","default":null,"default_function":"nextval('items_id_seq'::regclass)","primary":null,"coder":null},5337]],"line":222,"filename":"/Users/gafrong/flikr/app/controllers/items_controller.rb","method":"block in next_item"},"time":"2014-11-22T08:32:38.840+11:00","transaction_id":"84ce9093765909ee8727","end":"2014-11-22T08:32:38.840+11:00","children":[],"duration":0.491},{"name":"sql.active_record","payload":{"sql":"SELECT  \"items\".* FROM \"items\"  WHERE \"items\".\"id\" = $1 LIMIT 1","name":"Item Load","connection_id":70309411044380,"statement_name":"a3","binds":[[{"oid_type":{},"array":false,"name":"id","sql_type":"integer","null":false,"limit":null,"precision":null,"scale":null,"type":"integer","default":null,"default_function":"nextval('items_id_seq'::regclass)","primary":null,"coder":null},3932]],"line":222,"filename":"/Users/gafrong/flikr/app/controllers/items_controller.rb","method":"block in next_item"},"time":"2014-11-22T08:32:38.842+11:00","transaction_id":"84ce9093765909ee8727","end":"2014-11-22T08:32:38.843+11:00","children":[],"duration":0.501},{"name":"sql.active_record","payload":{"sql":"SELECT  \"items\".* FROM \"items\"  WHERE \"items\".\"id\" = $1 LIMIT 1","name":"Item Load","connection_id":70309411044380,"statement_name":"a3","binds":[[{"oid_type":{},"array":false,"name":"id","sql_type":"integer","null":false,"limit":null,"precision":null,"scale":null,"type":"integer","default":null,"default_function":"nextval('items_id_seq'::regclass)","primary":null,"coder":null},18284]],"line":222,"filename":"/Users/gafrong/flikr/app/controllers/items_controller.rb","method":"block in next_item"},"time":"2014-11-22T08:32:38.844+11:00","transaction_id":"84ce9093765909ee8727","end":"2014-11-22T08:32:38.845+11:00","children":[],"duration":0.486},{"name":"sql.active_record","payload":{"sql":"SELECT  \"items\".* FROM \"items\"  WHERE \"items\".\"id\" = $1 LIMIT 1","name":"Item Load","connection_id":70309411044380,"statement_name":"a3","binds":[[{"oid_type":{},"array":false,"name":"id","sql_type":"integer","null":false,"limit":null,"precision":null,"scale":null,"type":"integer","default":null,"default_function":"nextval('items_id_seq'::regclass)","primary":null,"coder":null},6833]],"line":222,"filename":"/Users/gafrong/flikr/app/controllers/items_controller.rb","method":"block in next_item"},"time":"2014-11-22T08:32:38.846+11:00","transaction_id":"84ce9093765909ee8727","end":"2014-11-22T08:32:38.847+11:00","children":[],"duration":0.486},{"name":"sql.active_record","payload":{"sql":"SELECT  \"items\".* FROM \"items\"  WHERE \"items\".\"id\" = $1 LIMIT 1","name":"Item Load","connection_id":70309411044380,"statement_name":"a3","binds":[[{"oid_type":{},"array":false,"name":"id","sql_type":"integer","null":false,"limit":null,"precision":null,"scale":null,"type":"integer","default":null,"default_function":"nextval('items_id_seq'::regclass)","primary":null,"coder":null},10580]],"line":222,"filename":"/Users/gafrong/flikr/app/controllers/items_controller.rb","method":"block in next_item"},"time":"2014-11-22T08:32:38.848+11:00","transaction_id":"84ce9093765909ee8727","end":"2014-11-22T08:32:38.849+11:00","children":[],"duration":0.47600000000000003},{"name":"sql.active_record","payload":{"sql":"SELECT  \"items\".* FROM \"items\"  WHERE \"items\".\"id\" = $1 LIMIT 1","name":"Item Load","connection_id":70309411044380,"statement_name":"a3","binds":[[{"oid_type":{},"array":false,"name":"id","sql_type":"integer","null":false,"limit":null,"precision":null,"scale":null,"type":"integer","default":null,"default_function":"nextval('items_id_seq'::regclass)","primary":null,"coder":null},17662]],"line":222,"filename":"/Users/gafrong/flikr/app/controllers/items_controller.rb","method":"block in next_item"},"time":"2014-11-22T08:32:38.850+11:00","transaction_id":"84ce9093765909ee8727","end":"2014-11-22T08:32:38.851+11:00","children":[],"duration":0.48500000000000004},{"name":"sql.active_record","payload":{"sql":"SELECT  \"items\".* FROM \"items\"  WHERE \"items\".\"id\" = $1 LIMIT 1","name":"Item Load","connection_id":70309411044380,"statement_name":"a3","binds":[[{"oid_type":{},"array":false,"name":"id","sql_type":"integer","null":false,"limit":null,"precision":null,"scale":null,"type":"integer","default":null,"default_function":"nextval('items_id_seq'::regclass)","primary":null,"coder":null},19311]],"line":222,"filename":"/Users/gafrong/flikr/app/controllers/items_controller.rb","method":"block in next_item"},"time":"2014-11-22T08:32:38.852+11:00","transaction_id":"84ce9093765909ee8727","end":"2014-11-22T08:32:38.853+11:00","children":[],"duration":0.49299999999999994},{"name":"sql.active_record","payload":{"sql":"SELECT \"items\".* FROM \"items\"  WHERE (gender='male' OR gender='unisex') AND \"items\".\"brand\" = 'Fred Perry'","name":"Item Load","connection_id":70309411044380,"statement_name":null,"binds":[],"line":253,"filename":"/Users/gafrong/flikr/app/controllers/items_controller.rb","method":"next_item"},"time":"2014-11-22T08:32:38.854+11:00","transaction_id":"84ce9093765909ee8727","end":"2014-11-22T08:32:38.864+11:00","children":[],"duration":10.077},{"name":"sql.active_record","payload":{"sql":"SELECT COUNT(*) FROM \"histories\"  WHERE \"histories\".\"user_id\" = $1","binds":[[{"oid_type":{},"array":false,"name":"user_id","sql_type":"integer","null":true,"limit":null,"precision":null,"scale":null,"type":"integer","default":null,"default_function":null,"primary":null,"coder":null},8]],"name":"CACHE","connection_id":70309411044380,"line":204,"filename":"/Users/gafrong/flikr/app/controllers/items_controller.rb","method":"next_item"},"time":"2014-11-22T08:32:38.867+11:00","transaction_id":"af2ba71234e02bb5d0b1","end":"2014-11-22T08:32:38.868+11:00","children":[],"duration":0.453},{"name":"sql.active_record","payload":{"sql":"SELECT \"histories\".* FROM \"histories\"  WHERE \"histories\".\"user_id\" = $1 AND \"histories\".\"liked\" = 't'","binds":[[{"oid_type":{},"array":false,"name":"user_id","sql_type":"integer","null":true,"limit":null,"precision":null,"scale":null,"type":"integer","default":null,"default_function":null,"primary":null,"coder":null},8]],"name":"CACHE","connection_id":70309411044380,"line":222,"filename":"/Users/gafrong/flikr/app/controllers/items_controller.rb","method":"next_item"},"time":"2014-11-22T08:32:38.870+11:00","transaction_id":"af2ba71234e02bb5d0b1","end":"2014-11-22T08:32:38.870+11:00","children":[],"duration":0.32},{"name":"sql.active_record","payload":{"sql":"SELECT  \"items\".* FROM \"items\"  WHERE \"items\".\"id\" = $1 LIMIT 1","binds":[[{"oid_type":{},"array":false,"name":"id","sql_type":"integer","null":false,"limit":null,"precision":null,"scale":null,"type":"integer","default":null,"default_function":"nextval('items_id_seq'::regclass)","primary":null,"coder":null},12204]],"name":"CACHE","connection_id":70309411044380,"line":222,"filename":"/Users/gafrong/flikr/app/controllers/items_controller.rb","method":"block in next_item"},"time":"2014-11-22T08:32:38.872+11:00","transaction_id":"af2ba71234e02bb5d0b1","end":"2014-11-22T08:32:38.872+11:00","children":[],"duration":0.219},{"name":"sql.active_record","payload":{"sql":"SELECT  \"items\".* FROM \"items\"  WHERE \"items\".\"id\" = $1 LIMIT 1","binds":[[{"oid_type":{},"array":false,"name":"id","sql_type":"integer","null":false,"limit":null,"precision":null,"scale":null,"type":"integer","default":null,"default_function":"nextval('items_id_seq'::regclass)","primary":null,"coder":null},5337]],"name":"CACHE","connection_id":70309411044380,"line":222,"filename":"/Users/gafrong/flikr/app/controllers/items_controller.rb","method":"block in next_item"},"time":"2014-11-22T08:32:38.873+11:00","transaction_id":"af2ba71234e02bb5d0b1","end":"2014-11-22T08:32:38.874+11:00","children":[],"duration":0.186},{"name":"sql.active_record","payload":{"sql":"SELECT  \"items\".* FROM \"items\"  WHERE \"items\".\"id\" = $1 LIMIT 1","binds":[[{"oid_type":{},"array":false,"name":"id","sql_type":"integer","null":false,"limit":null,"precision":null,"scale":null,"type":"integer","default":null,"default_function":"nextval('items_id_seq'::regclass)","primary":null,"coder":null},3932]],"name":"CACHE","connection_id":70309411044380,"line":222,"filename":"/Users/gafrong/flikr/app/controllers/items_controller.rb","method":"block in next_item"},"time":"2014-11-22T08:32:38.875+11:00","transaction_id":"af2ba71234e02bb5d0b1","end":"2014-11-22T08:32:38.875+11:00","children":[],"duration":0.18100000000000002},{"name":"sql.active_record","payload":{"sql":"SELECT  \"items\".* FROM \"items\"  WHERE \"items\".\"id\" = $1 LIMIT 1","binds":[[{"oid_type":{},"array":false,"name":"id","sql_type":"integer","null":false,"limit":null,"precision":null,"scale":null,"type":"integer","default":null,"default_function":"nextval('items_id_seq'::regclass)","primary":null,"coder":null},18284]],"name":"CACHE","connection_id":70309411044380,"line":222,"filename":"/Users/gafrong/flikr/app/controllers/items_controller.rb","method":"block in next_item"},"time":"2014-11-22T08:32:38.876+11:00","transaction_id":"af2ba71234e02bb5d0b1","end":"2014-11-22T08:32:38.885+11:00","children":[],"duration":8.983},{"name":"sql.active_record","payload":{"sql":"SELECT  \"items\".* FROM \"items\"  WHERE \"items\".\"id\" = $1 LIMIT 1","binds":[[{"oid_type":{},"array":false,"name":"id","sql_type":"integer","null":false,"limit":null,"precision":null,"scale":null,"type":"integer","default":null,"default_function":"nextval('items_id_seq'::regclass)","primary":null,"coder":null},6833]],"name":"CACHE","connection_id":70309411044380,"line":222,"filename":"/Users/gafrong/flikr/app/controllers/items_controller.rb","method":"block in next_item"},"time":"2014-11-22T08:32:38.888+11:00","transaction_id":"af2ba71234e02bb5d0b1","end":"2014-11-22T08:32:38.888+11:00","children":[],"duration":0.281},{"name":"sql.active_record","payload":{"sql":"SELECT  \"items\".* FROM \"items\"  WHERE \"items\".\"id\" = $1 LIMIT 1","binds":[[{"oid_type":{},"array":false,"name":"id","sql_type":"integer","null":false,"limit":null,"precision":null,"scale":null,"type":"integer","default":null,"default_function":"nextval('items_id_seq'::regclass)","primary":null,"coder":null},10580]],"name":"CACHE","connection_id":70309411044380,"line":222,"filename":"/Users/gafrong/flikr/app/controllers/items_controller.rb","method":"block in next_item"},"time":"2014-11-22T08:32:38.890+11:00","transaction_id":"af2ba71234e02bb5d0b1","end":"2014-11-22T08:32:38.890+11:00","children":[],"duration":0.255},{"name":"sql.active_record","payload":{"sql":"SELECT  \"items\".* FROM \"items\"  WHERE \"items\".\"id\" = $1 LIMIT 1","binds":[[{"oid_type":{},"array":false,"name":"id","sql_type":"integer","null":false,"limit":null,"precision":null,"scale":null,"type":"integer","default":null,"default_function":"nextval('items_id_seq'::regclass)","primary":null,"coder":null},17662]],"name":"CACHE","connection_id":70309411044380,"line":222,"filename":"/Users/gafrong/flikr/app/controllers/items_controller.rb","method":"block in next_item"},"time":"2014-11-22T08:32:38.892+11:00","transaction_id":"af2ba71234e02bb5d0b1","end":"2014-11-22T08:32:38.892+11:00","children":[],"duration":0.20900000000000002},{"name":"sql.active_record","payload":{"sql":"SELECT  \"items\".* FROM \"items\"  WHERE \"items\".\"id\" = $1 LIMIT 1","binds":[[{"oid_type":{},"array":false,"name":"id","sql_type":"integer","null":false,"limit":null,"precision":null,"scale":null,"type":"integer","default":null,"default_function":"nextval('items_id_seq'::regclass)","primary":null,"coder":null},19311]],"name":"CACHE","connection_id":70309411044380,"line":222,"filename":"/Users/gafrong/flikr/app/controllers/items_controller.rb","method":"block in next_item"},"time":"2014-11-22T08:32:38.893+11:00","transaction_id":"af2ba71234e02bb5d0b1","end":"2014-11-22T08:32:38.894+11:00","children":[],"duration":0.2},{"name":"sql.active_record","payload":{"sql":"SELECT \"items\".* FROM \"items\"  WHERE (gender='male' OR gender='unisex') AND \"items\".\"brand\" = 'DC Shoes'","name":"Item Load","connection_id":70309411044380,"statement_name":null,"binds":[],"line":253,"filename":"/Users/gafrong/flikr/app/controllers/items_controller.rb","method":"next_item"},"time":"2014-11-22T08:32:38.895+11:00","transaction_id":"84ce9093765909ee8727","end":"2014-11-22T08:32:38.906+11:00","children":[],"duration":10.697},{"name":"render_partial.action_view","payload":{"identifier":"/Users/gafrong/flikr/app/views/items/category/_history.html.erb"},"time":"2014-11-22T08:32:38.911+11:00","transaction_id":"af2ba71234e02bb5d0b1","end":"2014-11-22T08:32:38.912+11:00","children":[],"duration":1.4369999999999998},{"name":"render_partial.action_view","payload":{"identifier":"/Users/gafrong/flikr/app/views/items/category/_history_buy.html.erb"},"time":"2014-11-22T08:32:38.913+11:00","transaction_id":"af2ba71234e02bb5d0b1","end":"2014-11-22T08:32:38.913+11:00","children":[],"duration":0.565},{"name":"render_partial.action_view","payload":{"identifier":"/Users/gafrong/flikr/app/views/items/_color_all.html.erb"},"time":"2014-11-22T08:32:38.914+11:00","transaction_id":"af2ba71234e02bb5d0b1","end":"2014-11-22T08:32:38.915+11:00","children":[],"duration":1.452},{"name":"render_template.action_view","payload":{"identifier":"/Users/gafrong/flikr/app/views/items/category/show.html.erb","layout":"layouts/application"},"time":"2014-11-22T08:32:38.910+11:00","transaction_id":"af2ba71234e02bb5d0b1","end":"2014-11-22T08:32:38.915+11:00","children":[],"duration":5.172000000000001},{"name":"sql.active_record","payload":{"sql":"SELECT  \"users\".* FROM \"users\"  WHERE \"users\".\"id\" = 8 LIMIT 1","binds":[],"name":"CACHE","connection_id":70309411044380,"line":10,"filename":"/Users/gafrong/flikr/app/controllers/application_controller.rb","method":"current_user"},"time":"2014-11-22T08:32:40.502+11:00","transaction_id":"af2ba71234e02bb5d0b1","end":"2014-11-22T08:32:40.502+11:00","children":[],"duration":0.429},{"name":"sql.active_record","payload":{"sql":"SELECT  \"users\".* FROM \"users\"  WHERE \"users\".\"id\" = 8 LIMIT 1","binds":[],"name":"CACHE","connection_id":70309411044380,"line":10,"filename":"/Users/gafrong/flikr/app/controllers/application_controller.rb","method":"current_user"},"time":"2014-11-22T08:32:40.504+11:00","transaction_id":"af2ba71234e02bb5d0b1","end":"2014-11-22T08:32:40.504+11:00","children":[],"duration":0.261},{"name":"sql.active_record","payload":{"sql":"SELECT  \"users\".* FROM \"users\"  WHERE \"users\".\"id\" = 8 LIMIT 1","binds":[],"name":"CACHE","connection_id":70309411044380,"line":10,"filename":"/Users/gafrong/flikr/app/controllers/application_controller.rb","method":"current_user"},"time":"2014-11-22T08:32:40.505+11:00","transaction_id":"af2ba71234e02bb5d0b1","end":"2014-11-22T08:32:40.506+11:00","children":[],"duration":0.223},{"name":"sql.active_record","payload":{"sql":"SELECT  \"users\".* FROM \"users\"  WHERE \"users\".\"id\" = 8 LIMIT 1","binds":[],"name":"CACHE","connection_id":70309411044380,"line":10,"filename":"/Users/gafrong/flikr/app/controllers/application_controller.rb","method":"current_user"},"time":"2014-11-22T08:32:40.507+11:00","transaction_id":"af2ba71234e02bb5d0b1","end":"2014-11-22T08:32:40.507+11:00","children":[],"duration":0.248},{"name":"render_partial.action_view","payload":{"identifier":"/Users/gafrong/flikr/app/views/layouts/_navbar.html.erb"},"time":"2014-11-22T08:32:40.501+11:00","transaction_id":"af2ba71234e02bb5d0b1","end":"2014-11-22T08:32:40.509+11:00","children":[],"duration":8.046},{"name":"render_partial.action_view","payload":{"identifier":"/Users/gafrong/flikr/app/views/layouts/_footer.html.erb"},"time":"2014-11-22T08:32:40.510+11:00","transaction_id":"af2ba71234e02bb5d0b1","end":"2014-11-22T08:32:40.510+11:00","children":[],"duration":0.245},{"name":"process_action.action_controller","payload":{"controller":"ItemsController","action":"category_all","params":{"color":"","controller":"items","action":"category_all","gender":"mens"},"format":"html","method":"GET","path":"/items/category/mens/all?\u0026color=","status":200,"view_runtime":1601.388,"db_runtime":65.32700000000001},"time":"2014-11-22T08:32:38.618+11:00","transaction_id":"af2ba71234e02bb5d0b1","end":"2014-11-22T08:32:40.510+11:00","children":[],"duration":1892.7240000000002}]